pybulk/__init__.py
pybulk/base_db.py
pybulk/dbinterface.py
pybulk-0.2.21.dist-info/LICENSE
pybulk-0.2.21.dist-info/METADATA
pybulk-0.2.21.dist-info/WHEEL
pybulk-0.2.21.dist-info/top_level.txt
pybulk-0.2.21.dist-info/RECORD
