Metadata-Version: 2.1
Name: pybulk
Version: 0.2.21
Summary: PyBulk is a Python module that to allow simple and fast bulk data insertion into databases
Home-page: https://github.com/MrLpk/pybulk
Author: pengkailiao
Author-email: pengkailiao@gmail.com
Classifier: Programming Language :: Python :: 3
Classifier: Programming Language :: Python :: 3.6
Classifier: Programming Language :: Python :: 3.7
Classifier: Programming Language :: Python :: 3.8
Classifier: Programming Language :: Python :: 3.9
Classifier: Programming Language :: Python :: 3.10
Classifier: Programming Language :: Python :: 3.11
Classifier: License :: OSI Approved :: MIT License
Classifier: Operating System :: OS Independent
Requires-Python: >=3.6
License-File: LICENSE
Requires-Dist: PyMySQL >=0.9.3
Requires-Dist: SQLAlchemy <=2.0.0,>=1.3.8
